fantasyfootball/__init__.py
fantasyfootball/benchmarking.py
fantasyfootball/config.py
fantasyfootball/data.py
fantasyfootball/datasets/season/2015/calendar.gz
fantasyfootball/datasets/season/2015/defense.gz
fantasyfootball/datasets/season/2015/draft.gz
fantasyfootball/datasets/season/2015/injury.gz
fantasyfootball/datasets/season/2015/players.gz
fantasyfootball/datasets/season/2015/salary.gz
fantasyfootball/datasets/season/2015/stats.gz
fantasyfootball/datasets/season/2015/weather.gz
fantasyfootball/datasets/season/2016/calendar.gz
fantasyfootball/datasets/season/2016/defense.gz
fantasyfootball/datasets/season/2016/draft.gz
fantasyfootball/datasets/season/2016/injury.gz
fantasyfootball/datasets/season/2016/players.gz
fantasyfootball/datasets/season/2016/salary.gz
fantasyfootball/datasets/season/2016/stats.gz
fantasyfootball/datasets/season/2016/weather.gz
fantasyfootball/datasets/season/2017/calendar.gz
fantasyfootball/datasets/season/2017/defense.gz
fantasyfootball/datasets/season/2017/draft.gz
fantasyfootball/datasets/season/2017/injury.gz
fantasyfootball/datasets/season/2017/players.gz
fantasyfootball/datasets/season/2017/salary.gz
fantasyfootball/datasets/season/2017/stats.gz
fantasyfootball/datasets/season/2017/weather.gz
fantasyfootball/datasets/season/2018/calendar.gz
fantasyfootball/datasets/season/2018/defense.gz
fantasyfootball/datasets/season/2018/draft.gz
fantasyfootball/datasets/season/2018/injury.gz
fantasyfootball/datasets/season/2018/players.gz
fantasyfootball/datasets/season/2018/salary.gz
fantasyfootball/datasets/season/2018/stats.gz
fantasyfootball/datasets/season/2018/weather.gz
fantasyfootball/datasets/season/2019/calendar.gz
fantasyfootball/datasets/season/2019/defense.gz
fantasyfootball/datasets/season/2019/draft.gz
fantasyfootball/datasets/season/2019/injury.gz
fantasyfootball/datasets/season/2019/players.gz
fantasyfootball/datasets/season/2019/salary.gz
fantasyfootball/datasets/season/2019/stats.gz
fantasyfootball-0.4.26.dist-info/LICENSE
fantasyfootball-0.4.26.dist-info/WHEEL
fantasyfootball-0.4.26.dist-info/METADATA
fantasyfootball-0.4.26.dist-info/RECORD
