Metadata-Version: 2.1
Name: fantasyfootball
Version: 0.4.26
Summary: A package for Fantasy Football data and analysis
License: MIT
Author: Mark LeBoeuf
Requires-Python: >=3.7,<3.11
Classifier: License :: OSI Approved :: MIT License
Classifier: Programming Language :: Python :: 3
Classifier: Programming Language :: Python :: 3.7
Classifier: Programming Language :: Python :: 3.8
Classifier: Programming Language :: Python :: 3.9
Classifier: Programming Language :: Python :: 3.10
Requires-Dist: html5lib (>=1.1,<2.0)
Requires-Dist: jsonschema (>=4.17.3,<5.0.0)
Requires-Dist: lxml (>=4.7.1,<5.0.0)
Requires-Dist: openpyxl (>=3.0.9,<4.0.0)
Requires-Dist: pandas (>=1.3.5,<2.0.0) ; python_version >= "3.8" and python_version < "4.0"
Requires-Dist: pandas-flavor (>=0.2.0,<0.3.0)
Requires-Dist: pyjanitor (>=0.22.0,<0.23.0)
Requires-Dist: requests (>=2.27.1,<3.0.0)
Requires-Dist: scikit-learn (>=1.0.2,<2.0.0) ; python_version >= "3.8" and python_version < "4.0"
Requires-Dist: sklearn (>=0.0,<0.1)
